unicodeutil/Blocks.txt
unicodeutil/CaseFolding.txt
unicodeutil/HangulSyllableType.txt
unicodeutil/Jamo.txt
unicodeutil/UnicodeData.txt
unicodeutil/__init__.py
unicodeutil/hangulutil.py
unicodeutil/unicodeutil.py
unicodeutil-15.0a1.dist-info/LICENSE
unicodeutil-15.0a1.dist-info/METADATA
unicodeutil-15.0a1.dist-info/WHEEL
unicodeutil-15.0a1.dist-info/top_level.txt
unicodeutil-15.0a1.dist-info/RECORD
